repoly/__init__.py
repoly/app/__init__.py
repoly/app/client.py
repoly/app/main.py
repoly/geometry/__init__.py
repoly/geometry/abs/__init__.py
repoly/geometry/abs/mixin/__init__.py
repoly/geometry/abs/mixin/geoobj.py
repoly/geometry/entity.py
repoly/geometry/orientation.py
repoly/geometry/orientations.py
repoly/geometry/rectpoly.py
repoly/gui/__init__.py
repoly/gui/abs/__init__.py
repoly/gui/abs/form.py
repoly/gui/canvas.py
repoly/gui/entityform.py
repoly/gui/rectpolyform.py
repoly/gui/window.py
repoly-0.2102.41.dist-info/entry_points.txt
repoly-0.2102.41.dist-info/WHEEL
repoly-0.2102.41.dist-info/METADATA
repoly-0.2102.41.dist-info/RECORD
