Metadata-Version: 2.1
Name: repoly
Version: 0.2102.41
Summary: Rectilinear polygons
Author: davips
Author-email: dpsabc@gmail.com
Requires-Python: >=3.7.0,<3.8.0
Classifier: Programming Language :: Python :: 3
Classifier: Programming Language :: Python :: 3.7
Requires-Dist: PySide6 (>=6.0.1,<7.0.0)
Requires-Dist: python-dotenv (>=0.15.0,<0.16.0)
Requires-Dist: requests (>=2.25.1,<3.0.0)
